{
    "key": "group_67e58eee7ecba",
    "title": "Module: People",
    "fields": [
        {
            "key": "field_67e58eee43892",
            "label": "People Category",
            "name": "people_category",
            "aria-label": "",
            "type": "acfe_taxonomy_terms",
            "instructions": "",
            "required": 0,
            "conditional_logic": 0,
            "wrapper": {
                "width": "75",
                "class": "",
                "id": ""
            },
            "taxonomy": [
                "people_cat"
            ],
            "allow_terms": "",
            "allow_level": "",
            "field_type": "select",
            "default_value": [],
            "return_format": "name",
            "ui": 1,
            "allow_null": 0,
            "search_placeholder": "",
            "multiple": 0,
            "ajax": 0,
            "save_terms": 0,
            "load_terms": 0,
            "allow_in_bindings": 0,
            "choices": [],
            "placeholder": "",
            "layout": "",
            "toggle": 0,
            "allow_custom": 0,
            "other_choice": 0
        },
        {
            "key": "field_67e5a554e132c",
            "label": "Show Search",
            "name": "search",
            "aria-label": "",
            "type": "true_false",
            "instructions": "",
            "required": 0,
            "conditional_logic": 0,
            "wrapper": {
                "width": "25",
                "class": "",
                "id": ""
            },
            "message": "",
            "default_value": 1,
            "allow_in_bindings": 0,
            "ui_on_text": "",
            "ui_off_text": "",
            "ui": 1
        }
    ],
    "location": [
        [
            {
                "param": "post_type",
                "operator": "==",
                "value": "post"
            }
        ]
    ],
    "menu_order": 0,
    "position": "normal",
    "style": "default",
    "label_placement": "left",
    "instruction_placement": "label",
    "hide_on_screen": "",
    "active": false,
    "description": "",
    "show_in_rest": 0,
    "acfe_display_title": "",
    "acfe_autosync": [
        "json"
    ],
    "acfe_form": 0,
    "acfe_meta": "",
    "acfe_note": "",
    "modified": 1743103346
}
